stats_tm/__init__.py
stats_tm/distribution.py
stats_tm-1.0.3.dist-info/METADATA
stats_tm-1.0.3.dist-info/WHEEL
stats_tm-1.0.3.dist-info/license.txt
stats_tm-1.0.3.dist-info/top_level.txt
stats_tm-1.0.3.dist-info/RECORD
