Metadata-Version: 2.1
Name: stats-tm
Version: 1.0.3
Summary: package to visualize some statistical distributions and calculate their probability mass or density function along with their cumulative probability
Author: Timotius Marselo
Author-email: timotiusmarselo@gmail.com
License-File: license.txt
